{
  "Meta Data": {
      "1. Information": "Weekly Prices and Volumes for Digital Currency",
      "2. Digital Currency Code": "BTC",
      "3. Digital Currency Name": "Bitcoin",
      "4. Market Code": "CNY",
      "5. Market Name": "Chinese Yuan",
      "6. Last Refreshed": "2021-04-25 00:00:00",
      "7. Time Zone": "UTC"
  },
  "Time Series (Digital Currency Weekly)": {
      "2021-04-25": {
          "1a. open (CNY)": "364784.15496600",
          "1b. open (USD)": "56150.01000000",
          "2a. high (CNY)": "373728.67384600",
          "2b. high (USD)": "57526.81000000",
          "3a. low (CNY)": "308588.50000000",
          "3b. low (USD)": "47500.00000000",
          "4a. close (CNY)": "325812.48081800",
          "4b. close (USD)": "50151.23000000",
          "5. volume": "511965.75130300",
          "6. market cap (USD)": "511965.75130300"
      },
      "2021-04-18": {
          "1a. open (CNY)": "389788.20408000",
          "1b. open (USD)": "59998.80000000",
          "2a. high (CNY)": "421330.49640000",
          "2b. high (USD)": "64854.00000000",
          "3a. low (CNY)": "330880.28358000",
          "3b. low (USD)": "50931.30000000",
          "4a. close (CNY)": "364784.15496600",
          "4b. close (USD)": "56150.01000000",
          "5. volume": "549048.29803200",
          "6. market cap (USD)": "549048.29803200"
      }
  }
}