{
  "symbol": "TSLA",
  "annualReports": [
      {
          "fiscalDateEnding": "2020-12-31",
          "reportedCurrency": "USD",
          "totalAssets": "52148000000",
          "totalCurrentAssets": "26717000000",
          "cashAndCashEquivalentsAtCarryingValue": "19384000000",
          "cashAndShortTermInvestments": "19384000000",
          "inventory": "4101000000",
          "currentNetReceivables": "1895000000",
          "totalNonCurrentAssets": "18134000000",
          "propertyPlantEquipment": "12747000000",
          "accumulatedDepreciationAmortizationPPE": "5117000000",
          "intangibleAssets": "520000000",
          "intangibleAssetsExcludingGoodwill": "313000000",
          "goodwill": "207000000",
          "investments": "None",
          "longTermInvestments": "None",
          "shortTermInvestments": "None",
          "otherCurrentAssets": "1346000000",
          "otherNonCurrrentAssets": "1536000000",
          "totalLiabilities": "28418000000",
          "totalCurrentLiabilities": "14248000000",
          "currentAccountsPayable": "6051000000",
          "deferredRevenue": "4668000000",
          "currentDebt": "1758000000",
          "shortTermDebt": "2132000000",
          "totalNonCurrentLiabilities": "6962000000",
          "capitalLeaseObligations": "1094000000",
          "longTermDebt": "8462000000",
          "currentLongTermDebt": "2132000000",
          "longTermDebtNoncurrent": "None",
          "shortLongTermDebtTotal": "8462000000",
          "otherCurrentLiabilities": "241000000",
          "otherNonCurrentLiabilities": "3330000000",
          "totalShareholderEquity": "22225000000",
          "treasuryStock": "None",
          "retainedEarnings": "-5399000000",
          "commonStock": "1000000",
          "commonStockSharesOutstanding": "960000000"
      },
      {
          "fiscalDateEnding": "2019-12-31",
          "reportedCurrency": "USD",
          "totalAssets": "34309000000",
          "totalCurrentAssets": "12103000000",
          "cashAndCashEquivalentsAtCarryingValue": "6268000000",
          "cashAndShortTermInvestments": "6268000000",
          "inventory": "3552000000",
          "currentNetReceivables": "1333000000",
          "totalNonCurrentAssets": "15520000000",
          "propertyPlantEquipment": "10396000000",
          "accumulatedDepreciationAmortizationPPE": "3734000000",
          "intangibleAssets": "537000000",
          "intangibleAssetsExcludingGoodwill": "339000000",
          "goodwill": "198000000",
          "investments": "None",
          "longTermInvestments": "1000000",
          "shortTermInvestments": "None",
          "otherCurrentAssets": "246000000",
          "otherNonCurrrentAssets": "1470000000",
          "totalLiabilities": "26199000000",
          "totalCurrentLiabilities": "10667000000",
          "currentAccountsPayable": "3771000000",
          "deferredRevenue": "3842000000",
          "currentDebt": "1399000000",
          "shortTermDebt": "1785000000",
          "totalNonCurrentLiabilities": "6086000000",
          "capitalLeaseObligations": "1232000000",
          "longTermDebt": "10402000000",
          "currentLongTermDebt": "1785000000",
          "longTermDebtNoncurrent": "None",
          "shortLongTermDebtTotal": "10402000000",
          "otherCurrentLiabilities": "260000000",
          "otherNonCurrentLiabilities": "2691000000",
          "totalShareholderEquity": "6618000000",
          "treasuryStock": "None",
          "retainedEarnings": "-6083000000",
          "commonStock": "1000000",
          "commonStockSharesOutstanding": "181000000"
      },
      {
          "fiscalDateEnding": "2018-12-31",
          "reportedCurrency": "USD",
          "totalAssets": "29740000000",
          "totalCurrentAssets": "8307000000",
          "cashAndCashEquivalentsAtCarryingValue": "3686000000",
          "cashAndShortTermInvestments": "3686000000",
          "inventory": "3113000000",
          "currentNetReceivables": "949000000",
          "totalNonCurrentAssets": "398000000",
          "propertyPlantEquipment": "11330000000",
          "accumulatedDepreciationAmortizationPPE": "2699000000",
          "intangibleAssets": "350000000",
          "intangibleAssetsExcludingGoodwill": "282000000",
          "goodwill": "68000000",
          "investments": "None",
          "longTermInvestments": "421548000",
          "shortTermInvestments": "192551000",
          "otherCurrentAssets": "558222000",
          "otherNonCurrrentAssets": "572000000",
          "totalLiabilities": "23427000000",
          "totalCurrentLiabilities": "9993000000",
          "currentAccountsPayable": "3405000000",
          "deferredRevenue": "883000000",
          "currentDebt": "2222000000",
          "shortTermDebt": "2567699000",
          "totalNonCurrentLiabilities": "3760000000",
          "capitalLeaseObligations": "1855900000",
          "longTermDebt": "8411000000",
          "currentLongTermDebt": "2567699000",
          "longTermDebtNoncurrent": "None",
          "shortLongTermDebtTotal": "8411000000",
          "otherCurrentLiabilities": "372000000",
          "otherNonCurrentLiabilities": "2710000000",
          "totalShareholderEquity": "4923243000",
          "treasuryStock": "None",
          "retainedEarnings": "-5317832000",
          "commonStock": "173000",
          "commonStockSharesOutstanding": "172603000"
      },
      {
          "fiscalDateEnding": "2017-12-31",
          "reportedCurrency": "USD",
          "totalAssets": "28655372000",
          "totalCurrentAssets": "6570520000",
          "cashAndCashEquivalentsAtCarryingValue": "3368000000",
          "cashAndShortTermInvestments": "3368000000",
          "inventory": "2263537000",
          "currentNetReceivables": "515381000",
          "totalNonCurrentAssets": "442000000",
          "propertyPlantEquipment": "10027522000",
          "accumulatedDepreciationAmortizationPPE": "1723794000",
          "intangibleAssets": "421739000",
          "intangibleAssetsExcludingGoodwill": "361502000",
          "goodwill": "60237000",
          "investments": "None",
          "longTermInvestments": "456652000",
          "shortTermInvestments": "155323000",
          "otherCurrentAssets": "423688000",
          "otherNonCurrrentAssets": "273123000",
          "totalLiabilities": "23022980000",
          "totalCurrentLiabilities": "7674670000",
          "currentAccountsPayable": "2390250000",
          "deferredRevenue": "476000000",
          "currentDebt": "799849000",
          "shortTermDebt": "896549000",
          "totalNonCurrentLiabilities": "13085908000",
          "capitalLeaseObligations": "1801010000",
          "longTermDebt": "8828985000",
          "currentLongTermDebt": "796549000",
          "longTermDebtNoncurrent": "None",
          "shortLongTermDebtTotal": "8828985000",
          "otherCurrentLiabilities": "130565000",
          "otherNonCurrentLiabilities": "2442970000",
          "totalShareholderEquity": "4237242000",
          "treasuryStock": "None",
          "retainedEarnings": "-4974299000",
          "commonStock": "169000",
          "commonStockSharesOutstanding": "168797000"
      },
      {
          "fiscalDateEnding": "2016-12-31",
          "reportedCurrency": "USD",
          "totalAssets": "22664076000",
          "totalCurrentAssets": "6259796000",
          "cashAndCashEquivalentsAtCarryingValue": "3393000000",
          "cashAndShortTermInvestments": "3393000000",
          "inventory": "2067454000",
          "currentNetReceivables": "499142000",
          "totalNonCurrentAssets": "268000000",
          "propertyPlantEquipment": "5982957000",
          "accumulatedDepreciationAmortizationPPE": "997485000",
          "intangibleAssets": "376145000",
          "intangibleAssetsExcludingGoodwill": "376145000",
          "goodwill": "None",
          "investments": "None",
          "longTermInvestments": "506302000",
          "shortTermInvestments": "105519000",
          "otherCurrentAssets": "194465000",
          "otherNonCurrrentAssets": "216751000",
          "totalLiabilities": "16750167000",
          "totalCurrentLiabilities": "5827005000",
          "currentAccountsPayable": "1860341000",
          "deferredRevenue": "1614916000",
          "currentDebt": "1114652000",
          "shortTermDebt": "1150147000",
          "totalNonCurrentLiabilities": "8640254000",
          "capitalLeaseObligations": "1459684000",
          "longTermDebt": "5892016000",
          "currentLongTermDebt": "984211000",
          "longTermDebtNoncurrent": "None",
          "shortLongTermDebtTotal": "5892016000",
          "otherCurrentLiabilities": "84492000",
          "otherNonCurrentLiabilities": "1891449000",
          "totalShareholderEquity": "4752911000",
          "treasuryStock": "None",
          "retainedEarnings": "-2997237000",
          "commonStock": "161000",
          "commonStockSharesOutstanding": "161561000"
      }
  ],
  "quarterlyReports": [
      {
          "fiscalDateEnding": "2020-12-31",
          "reportedCurrency": "USD",
          "totalAssets": "52148000000",
          "totalCurrentAssets": "26717000000",
          "cashAndCashEquivalentsAtCarryingValue": "19384000000",
          "cashAndShortTermInvestments": "19384000000",
          "inventory": "4101000000",
          "currentNetReceivables": "1895000000",
          "totalNonCurrentAssets": "18134000000",
          "propertyPlantEquipment": "12747000000",
          "accumulatedDepreciationAmortizationPPE": "5117000000",
          "intangibleAssets": "520000000",
          "intangibleAssetsExcludingGoodwill": "313000000",
          "goodwill": "207000000",
          "investments": "None",
          "longTermInvestments": "None",
          "shortTermInvestments": "None",
          "otherCurrentAssets": "1346000000",
          "otherNonCurrrentAssets": "1536000000",
          "totalLiabilities": "28418000000",
          "totalCurrentLiabilities": "14248000000",
          "currentAccountsPayable": "6051000000",
          "deferredRevenue": "4668000000",
          "currentDebt": "1758000000",
          "shortTermDebt": "2132000000",
          "totalNonCurrentLiabilities": "6962000000",
          "capitalLeaseObligations": "1094000000",
          "longTermDebt": "8462000000",
          "currentLongTermDebt": "2132000000",
          "longTermDebtNoncurrent": "None",
          "shortLongTermDebtTotal": "8462000000",
          "otherCurrentLiabilities": "241000000",
          "otherNonCurrentLiabilities": "3330000000",
          "totalShareholderEquity": "22225000000",
          "treasuryStock": "None",
          "retainedEarnings": "-5399000000",
          "commonStock": "1000000",
          "commonStockSharesOutstanding": "960000000"
      },
      {
          "fiscalDateEnding": "2020-09-30",
          "reportedCurrency": "USD",
          "totalAssets": "45691000000",
          "totalCurrentAssets": "21744000000",
          "cashAndCashEquivalentsAtCarryingValue": "14531000000",
          "cashAndShortTermInvestments": "14531000000",
          "inventory": "4218000000",
          "currentNetReceivables": "1766000000",
          "totalNonCurrentAssets": "15478000000",
          "propertyPlantEquipment": "11848000000",
          "accumulatedDepreciationAmortizationPPE": "4814000000",
          "intangibleAssets": "521000000",
          "intangibleAssetsExcludingGoodwill": "318000000",
          "goodwill": "203000000",
          "investments": "None",
          "longTermInvestments": "None",
          "shortTermInvestments": "None",
          "otherCurrentAssets": "1238000000",
          "otherNonCurrrentAssets": "1436000000",
          "totalLiabilities": "28143000000",
          "totalCurrentLiabilities": "13302000000",
          "currentAccountsPayable": "4958000000",
          "deferredRevenue": "4221000000",
          "currentDebt": "2766000000",
          "shortTermDebt": "2766000000",
          "totalNonCurrentLiabilities": "6514000000",
          "capitalLeaseObligations": "1131000000",
          "longTermDebt": "9428000000",
          "currentLongTermDebt": "2766000000",
          "longTermDebtNoncurrent": "None",
          "shortLongTermDebtTotal": "9428000000",
          "otherCurrentLiabilities": "173000000",
          "otherNonCurrentLiabilities": "3049000000",
          "totalShareholderEquity": "16031000000",
          "treasuryStock": "None",
          "retainedEarnings": "-5669000000",
          "commonStock": "1000000",
          "commonStockSharesOutstanding": "948000000"
      },
      {
          "fiscalDateEnding": "2020-06-30",
          "reportedCurrency": "USD",
          "totalAssets": "38135000000",
          "totalCurrentAssets": "15336000000",
          "cashAndCashEquivalentsAtCarryingValue": "8615000000",
          "cashAndShortTermInvestments": "8615000000",
          "inventory": "4018000000",
          "currentNetReceivables": "1495000000",
          "totalNonCurrentAssets": "14845000000",
          "propertyPlantEquipment": "11009000000",
          "accumulatedDepreciationAmortizationPPE": "4430000000",
          "intangibleAssets": "508000000",
          "intangibleAssetsExcludingGoodwill": "312000000",
          "goodwill": "196000000",
          "investments": "None",
          "longTermInvestments": "None",
          "shortTermInvestments": "None",
          "otherCurrentAssets": "1218000000",
          "otherNonCurrrentAssets": "1415000000",
          "totalLiabilities": "26754000000",
          "totalCurrentLiabilities": "12270000000",
          "currentAccountsPayable": "3638000000",
          "deferredRevenue": "3938000000",
          "currentDebt": "3317000000",
          "shortTermDebt": "3317000000",
          "totalNonCurrentLiabilities": "6253000000",
          "capitalLeaseObligations": "1169000000",
          "longTermDebt": "9247000000",
          "currentLongTermDebt": "233000000",
          "longTermDebtNoncurrent": "None",
          "shortLongTermDebtTotal": "9247000000",
          "otherCurrentLiabilities": "179000000",
          "otherNonCurrentLiabilities": "2870000000",
          "totalShareholderEquity": "9855000000",
          "treasuryStock": "None",
          "retainedEarnings": "-6000000000",
          "commonStock": "186000",
          "commonStockSharesOutstanding": "186000000"
      },
      {
          "fiscalDateEnding": "2020-03-31",
          "reportedCurrency": "USD",
          "totalAssets": "37250000000",
          "totalCurrentAssets": "14893000000",
          "cashAndCashEquivalentsAtCarryingValue": "8080000000",
          "cashAndShortTermInvestments": "8080000000",
          "inventory": "4494000000",
          "currentNetReceivables": "1283000000",
          "totalNonCurrentAssets": "14356000000",
          "propertyPlantEquipment": "10638000000",
          "accumulatedDepreciationAmortizationPPE": "4072000000",
          "intangibleAssets": "516000000",
          "intangibleAssetsExcludingGoodwill": "323000000",
          "goodwill": "193000000",
          "investments": "None",
          "longTermInvestments": "None",
          "shortTermInvestments": "None",
          "otherCurrentAssets": "1045000000",
          "otherNonCurrrentAssets": "1373000000",
          "totalLiabilities": "26518000000",
          "totalCurrentLiabilities": "11986000000",
          "currentAccountsPayable": "3970000000",
          "deferredRevenue": "3915000000",
          "currentDebt": "2851000000",
          "shortTermDebt": "2851000000",
          "totalNonCurrentLiabilities": "5994000000",
          "capitalLeaseObligations": "1187000000",
          "longTermDebt": "9479000000",
          "currentLongTermDebt": "229000000",
          "longTermDebtNoncurrent": "None",
          "shortLongTermDebtTotal": "9479000000",
          "otherCurrentLiabilities": "184000000",
          "otherNonCurrentLiabilities": "2667000000",
          "totalShareholderEquity": "9173000000",
          "treasuryStock": "None",
          "retainedEarnings": "-6104000000",
          "commonStock": "185000",
          "commonStockSharesOutstanding": "185000000"
      },
      {
          "fiscalDateEnding": "2019-12-31",
          "reportedCurrency": "USD",
          "totalAssets": "34309000000",
          "totalCurrentAssets": "12103000000",
          "cashAndCashEquivalentsAtCarryingValue": "6268000000",
          "cashAndShortTermInvestments": "6268000000",
          "inventory": "3552000000",
          "currentNetReceivables": "1333000000",
          "totalNonCurrentAssets": "15520000000",
          "propertyPlantEquipment": "10396000000",
          "accumulatedDepreciationAmortizationPPE": "3734000000",
          "intangibleAssets": "537000000",
          "intangibleAssetsExcludingGoodwill": "339000000",
          "goodwill": "198000000",
          "investments": "None",
          "longTermInvestments": "1000000",
          "shortTermInvestments": "None",
          "otherCurrentAssets": "246000000",
          "otherNonCurrrentAssets": "1470000000",
          "totalLiabilities": "26199000000",
          "totalCurrentLiabilities": "10667000000",
          "currentAccountsPayable": "3771000000",
          "deferredRevenue": "3842000000",
          "currentDebt": "1399000000",
          "shortTermDebt": "1785000000",
          "totalNonCurrentLiabilities": "6086000000",
          "capitalLeaseObligations": "1232000000",
          "longTermDebt": "10402000000",
          "currentLongTermDebt": "1785000000",
          "longTermDebtNoncurrent": "None",
          "shortLongTermDebtTotal": "10402000000",
          "otherCurrentLiabilities": "260000000",
          "otherNonCurrentLiabilities": "2691000000",
          "totalShareholderEquity": "6618000000",
          "treasuryStock": "None",
          "retainedEarnings": "-6083000000",
          "commonStock": "181000",
          "commonStockSharesOutstanding": "181000000"
      },
      {
          "fiscalDateEnding": "2019-09-30",
          "reportedCurrency": "USD",
          "totalAssets": "32795000000",
          "totalCurrentAssets": "10940000000",
          "cashAndCashEquivalentsAtCarryingValue": "5338000000",
          "cashAndShortTermInvestments": "5338000000",
          "inventory": "3581000000",
          "currentNetReceivables": "1128000000",
          "totalNonCurrentAssets": "255000000",
          "propertyPlantEquipment": "10190000000",
          "accumulatedDepreciationAmortizationPPE": "3528000000",
          "intangibleAssets": "537000000",
          "intangibleAssetsExcludingGoodwill": "351000000",
          "goodwill": "186000000",
          "investments": "None",
          "longTermInvestments": "398000000",
          "shortTermInvestments": "None",
          "otherCurrentAssets": "893000000",
          "otherNonCurrrentAssets": "820000000",
          "totalLiabilities": "25313000000",
          "totalCurrentLiabilities": "10146000000",
          "currentAccountsPayable": "3468000000",
          "deferredRevenue": "3485000000",
          "currentDebt": "1643000000",
          "shortTermDebt": "2030000000",
          "totalNonCurrentLiabilities": "6061000000",
          "capitalLeaseObligations": "1217000000",
          "longTermDebt": "10096000000",
          "currentLongTermDebt": "223000000",
          "longTermDebtNoncurrent": "None",
          "shortLongTermDebtTotal": "10096000000",
          "otherCurrentLiabilities": "441000000",
          "otherNonCurrentLiabilities": "2676000000",
          "totalShareholderEquity": "6040000000",
          "treasuryStock": "None",
          "retainedEarnings": "-6188000000",
          "commonStock": "180000",
          "commonStockSharesOutstanding": "180000000"
      },
      {
          "fiscalDateEnding": "2019-06-30",
          "reportedCurrency": "USD",
          "totalAssets": "31872597000",
          "totalCurrentAssets": "10181952000",
          "cashAndCashEquivalentsAtCarryingValue": "4955000000",
          "cashAndShortTermInvestments": "4955000000",
          "inventory": "3382358000",
          "currentNetReceivables": "1147100000",
          "totalNonCurrentAssets": "366000000",
          "propertyPlantEquipment": "10082458000",
          "accumulatedDepreciationAmortizationPPE": "3248310000",
          "intangibleAssets": "480833000",
          "intangibleAssetsExcludingGoodwill": "327358000",
          "goodwill": "153475000",
          "investments": "None",
          "longTermInvestments": "400308000",
          "shortTermInvestments": "None",
          "otherCurrentAssets": "697754000",
          "otherNonCurrrentAssets": "842978000",
          "totalLiabilities": "24722136000",
          "totalCurrentLiabilities": "9588773000",
          "currentAccountsPayable": "3133587000",
          "deferredRevenue": "None",
          "currentDebt": "1459828000",
          "shortTermDebt": "1791085000",
          "totalNonCurrentLiabilities": "3837762000",
          "capitalLeaseObligations": "1328554000",
          "longTermDebt": "9905847000",
          "currentLongTermDebt": "1791085000",
          "longTermDebtNoncurrent": "None",
          "shortLongTermDebtTotal": "9905847000",
          "otherCurrentLiabilities": "526758000",
          "otherNonCurrentLiabilities": "2655720000",
          "totalShareholderEquity": "5715393000",
          "treasuryStock": "None",
          "retainedEarnings": "-6331639000",
          "commonStock": "179000",
          "commonStockSharesOutstanding": "179118000"
      },
      {
          "fiscalDateEnding": "2019-03-31",
          "reportedCurrency": "USD",
          "totalAssets": "28912524000",
          "totalCurrentAssets": "7677822000",
          "cashAndCashEquivalentsAtCarryingValue": "2198000000",
          "cashAndShortTermInvestments": "2198000000",
          "inventory": "3836850000",
          "currentNetReceivables": "1046945000",
          "totalNonCurrentAssets": "354000000",
          "propertyPlantEquipment": "9850929000",
          "accumulatedDepreciationAmortizationPPE": "2918587000",
          "intangibleAssets": "347880000",
          "intangibleAssetsExcludingGoodwill": "273568000",
          "goodwill": "74312000",
          "investments": "None",
          "longTermInvestments": "413181000",
          "shortTermInvestments": "None",
          "otherCurrentAssets": "595858000",
          "otherNonCurrrentAssets": "801867000",
          "totalLiabilities": "22874618000",
          "totalCurrentLiabilities": "9242800000",
          "currentAccountsPayable": "3248827000",
          "deferredRevenue": "None",
          "currentDebt": "1352596000",
          "shortTermDebt": "1705711000",
          "totalNonCurrentLiabilities": "3632478000",
          "capitalLeaseObligations": "1137927000",
          "longTermDebt": "8650023000",
          "currentLongTermDebt": "1705711000",
          "longTermDebtNoncurrent": "None",
          "shortLongTermDebtTotal": "8650023000",
          "otherCurrentLiabilities": "3717022000",
          "otherNonCurrentLiabilities": "2475135000",
          "totalShareholderEquity": "4605596000",
          "treasuryStock": "None",
          "retainedEarnings": "-5923305000",
          "commonStock": "174000",
          "commonStockSharesOutstanding": "173682000"
      },
      {
          "fiscalDateEnding": "2018-12-31",
          "reportedCurrency": "USD",
          "totalAssets": "29740000000",
          "totalCurrentAssets": "8307000000",
          "cashAndCashEquivalentsAtCarryingValue": "3686000000",
          "cashAndShortTermInvestments": "3686000000",
          "inventory": "3113000000",
          "currentNetReceivables": "949000000",
          "totalNonCurrentAssets": "398000000",
          "propertyPlantEquipment": "11330000000",
          "accumulatedDepreciationAmortizationPPE": "2699000000",
          "intangibleAssets": "350000000",
          "intangibleAssetsExcludingGoodwill": "282000000",
          "goodwill": "68000000",
          "investments": "None",
          "longTermInvestments": "421548000",
          "shortTermInvestments": "192551000",
          "otherCurrentAssets": "558222000",
          "otherNonCurrrentAssets": "572000000",
          "totalLiabilities": "23427000000",
          "totalCurrentLiabilities": "9993000000",
          "currentAccountsPayable": "3405000000",
          "deferredRevenue": "None",
          "currentDebt": "2222000000",
          "shortTermDebt": "2567699000",
          "totalNonCurrentLiabilities": "3760000000",
          "capitalLeaseObligations": "None",
          "longTermDebt": "8411000000",
          "currentLongTermDebt": "2283746000",
          "longTermDebtNoncurrent": "None",
          "shortLongTermDebtTotal": "8411000000",
          "otherCurrentLiabilities": "1925733000",
          "otherNonCurrentLiabilities": "2710000000",
          "totalShareholderEquity": "4923243000",
          "treasuryStock": "None",
          "retainedEarnings": "-5317832000",
          "commonStock": "173000",
          "commonStockSharesOutstanding": "172603000"
      },
      {
          "fiscalDateEnding": "2018-09-30",
          "reportedCurrency": "USD",
          "totalAssets": "29262713000",
          "totalCurrentAssets": "7920491000",
          "cashAndCashEquivalentsAtCarryingValue": "2967000000",
          "cashAndShortTermInvestments": "2967000000",
          "inventory": "3314127000",
          "currentNetReceivables": "1155001000",
          "totalNonCurrentAssets": "397000000",
          "propertyPlantEquipment": "11246295000",
          "accumulatedDepreciationAmortizationPPE": "2454339000",
          "intangibleAssets": "356702000",
          "intangibleAssetsExcludingGoodwill": "291476000",
          "goodwill": "65226000",
          "investments": "None",
          "longTermInvestments": "422897000",
          "shortTermInvestments": "158627000",
          "otherCurrentAssets": "483859000",
          "otherNonCurrrentAssets": "431819000",
          "totalLiabilities": "23409144000",
          "totalCurrentLiabilities": "9775324000",
          "currentAccountsPayable": "3596984000",
          "deferredRevenue": "None",
          "currentDebt": "1833475000",
          "shortTermDebt": "2106538000",
          "totalNonCurrentLiabilities": "13232967000",
          "capitalLeaseObligations": "None",
          "longTermDebt": "8665163000",
          "currentLongTermDebt": "2106538000",
          "longTermDebtNoncurrent": "None",
          "shortLongTermDebtTotal": "8665163000",
          "otherCurrentLiabilities": "2081707000",
          "otherNonCurrentLiabilities": "2555319000",
          "totalShareholderEquity": "4508838000",
          "treasuryStock": "None",
          "retainedEarnings": "-5457315000",
          "commonStock": "171000",
          "commonStockSharesOutstanding": "171578000"
      },
      {
          "fiscalDateEnding": "2018-06-30",
          "reportedCurrency": "USD",
          "totalAssets": "27910000000",
          "totalCurrentAssets": "6699797000",
          "cashAndCashEquivalentsAtCarryingValue": "2236424000",
          "cashAndShortTermInvestments": "2236424000",
          "inventory": "3324643000",
          "currentNetReceivables": "569874000",
          "totalNonCurrentAssets": "399992000",
          "propertyPlantEquipment": "10969348000",
          "accumulatedDepreciationAmortizationPPE": "2188723000",
          "intangibleAssets": "364690000",
          "intangibleAssetsExcludingGoodwill": "300406000",
          "goodwill": "64284000",
          "investments": "None",
          "longTermInvestments": "434841000",
          "shortTermInvestments": "146822000",
          "otherCurrentAssets": "568856000",
          "otherNonCurrrentAssets": "419254000",
          "totalLiabilities": "22642887000",
          "totalCurrentLiabilities": "9141362000",
          "currentAccountsPayable": "3030493000",
          "deferredRevenue": "None",
          "currentDebt": "1838909000",
          "shortTermDebt": "2103185000",
          "totalNonCurrentLiabilities": "12171812000",
          "capitalLeaseObligations": "None",
          "longTermDebt": "8626114000",
          "currentLongTermDebt": "2103185000",
          "longTermDebtNoncurrent": "None",
          "shortLongTermDebtTotal": "8626114000",
          "otherCurrentLiabilities": "2192705000",
          "otherNonCurrentLiabilities": "2607458000",
          "totalShareholderEquity": "3906421000",
          "treasuryStock": "None",
          "retainedEarnings": "-5768831000",
          "commonStock": "170000",
          "commonStockSharesOutstanding": "170516000"
      },
      {
          "fiscalDateEnding": "2018-03-31",
          "reportedCurrency": "USD",
          "totalAssets": "27271429000",
          "totalCurrentAssets": "6383920000",
          "cashAndCashEquivalentsAtCarryingValue": "2665673000",
          "cashAndShortTermInvestments": "2665673000",
          "inventory": "2565826000",
          "currentNetReceivables": "652848000",
          "totalNonCurrentAssets": "433841000",
          "propertyPlantEquipment": "10519226000",
          "accumulatedDepreciationAmortizationPPE": "1992548000",
          "intangibleAssets": "407712000",
          "intangibleAssetsExcludingGoodwill": "346428000",
          "goodwill": "61284000",
          "investments": "None",
          "longTermInvestments": "449754000",
          "shortTermInvestments": "120194000",
          "otherCurrentAssets": "499573000",
          "otherNonCurrrentAssets": "415478000",
          "totalLiabilities": "21551021000",
          "totalCurrentLiabilities": "8650359000",
          "currentAccountsPayable": "2603498000",
          "deferredRevenue": "None",
          "currentDebt": "1755634000",
          "shortTermDebt": "1998030000",
          "totalNonCurrentLiabilities": "12193428000",
          "capitalLeaseObligations": "None",
          "longTermDebt": "8219577000",
          "currentLongTermDebt": "1998032000",
          "longTermDebtNoncurrent": "None",
          "shortLongTermDebtTotal": "8219577000",
          "otherCurrentLiabilities": "2150400000",
          "otherNonCurrentLiabilities": "2561886000",
          "totalShareholderEquity": "4450695000",
          "treasuryStock": "None",
          "retainedEarnings": "-5051292000",
          "commonStock": "170000",
          "commonStockSharesOutstanding": "169750000"
      },
      {
          "fiscalDateEnding": "2017-12-31",
          "reportedCurrency": "USD",
          "totalAssets": "28655372000",
          "totalCurrentAssets": "6570520000",
          "cashAndCashEquivalentsAtCarryingValue": "3368000000",
          "cashAndShortTermInvestments": "3368000000",
          "inventory": "2263537000",
          "currentNetReceivables": "515381000",
          "totalNonCurrentAssets": "442000000",
          "propertyPlantEquipment": "10027522000",
          "accumulatedDepreciationAmortizationPPE": "1723794000",
          "intangibleAssets": "421739000",
          "intangibleAssetsExcludingGoodwill": "361502000",
          "goodwill": "60237000",
          "investments": "None",
          "longTermInvestments": "456652000",
          "shortTermInvestments": "155323000",
          "otherCurrentAssets": "423688000",
          "otherNonCurrrentAssets": "273123000",
          "totalLiabilities": "23022980000",
          "totalCurrentLiabilities": "7674670000",
          "currentAccountsPayable": "2390250000",
          "deferredRevenue": "None",
          "currentDebt": "799849000",
          "shortTermDebt": "896549000",
          "totalNonCurrentLiabilities": "13085908000",
          "capitalLeaseObligations": "None",
          "longTermDebt": "8828985000",
          "currentLongTermDebt": "963932000",
          "longTermDebtNoncurrent": "None",
          "shortLongTermDebtTotal": "8828985000",
          "otherCurrentLiabilities": "2656505000",
          "otherNonCurrentLiabilities": "2442970000",
          "totalShareholderEquity": "4237242000",
          "treasuryStock": "None",
          "retainedEarnings": "-4974299000",
          "commonStock": "169000",
          "commonStockSharesOutstanding": "168797000"
      },
      {
          "fiscalDateEnding": "2017-09-30",
          "reportedCurrency": "USD",
          "totalAssets": "28107074000",
          "totalCurrentAssets": "7068733000",
          "cashAndCashEquivalentsAtCarryingValue": "3530030000",
          "cashAndShortTermInvestments": "3530030000",
          "inventory": "2471382000",
          "currentNetReceivables": "607734000",
          "totalNonCurrentAssets": "408544000",
          "propertyPlantEquipment": "9394397000",
          "accumulatedDepreciationAmortizationPPE": "1535561000",
          "intangibleAssets": "417474000",
          "intangibleAssetsExcludingGoodwill": "372238000",
          "goodwill": "45236000",
          "investments": "None",
          "longTermInvestments": "463878000",
          "shortTermInvestments": "138181000",
          "otherCurrentAssets": "459587000",
          "otherNonCurrrentAssets": "231849000",
          "totalLiabilities": "21929057000",
          "totalCurrentLiabilities": "6468940000",
          "currentAccountsPayable": "2385778000",
          "deferredRevenue": "None",
          "currentDebt": "375506000",
          "shortTermDebt": "424224000",
          "totalNonCurrentLiabilities": "13090449000",
          "capitalLeaseObligations": "None",
          "longTermDebt": "9049729000",
          "currentLongTermDebt": "424581000",
          "longTermDebtNoncurrent": "None",
          "shortLongTermDebtTotal": "9049729000",
          "otherCurrentLiabilities": "2181154000",
          "otherNonCurrentLiabilities": "2382830000",
          "totalShareholderEquity": "4711480000",
          "treasuryStock": "None",
          "retainedEarnings": "-4298960000",
          "commonStock": "168000",
          "commonStockSharesOutstanding": "168017000"
      },
      {
          "fiscalDateEnding": "2017-06-30",
          "reportedCurrency": "USD",
          "totalAssets": "26043705000",
          "totalCurrentAssets": "6359444000",
          "cashAndCashEquivalentsAtCarryingValue": "3035924000",
          "cashAndShortTermInvestments": "3035924000",
          "inventory": "2438111000",
          "currentNetReceivables": "453539000",
          "totalNonCurrentAssets": "358445000",
          "propertyPlantEquipment": "8399229000",
          "accumulatedDepreciationAmortizationPPE": "1337411000",
          "intangibleAssets": "424613000",
          "intangibleAssetsExcludingGoodwill": "380847000",
          "goodwill": "43766000",
          "investments": "None",
          "longTermInvestments": "472663000",
          "shortTermInvestments": "118369000",
          "otherCurrentAssets": "431870000",
          "otherNonCurrrentAssets": "209986000",
          "totalLiabilities": "19459902000",
          "totalCurrentLiabilities": "6546355000",
          "currentAccountsPayable": "2359316000",
          "deferredRevenue": "None",
          "currentDebt": "760284000",
          "shortTermDebt": "816533000",
          "totalNonCurrentLiabilities": "10455599000",
          "capitalLeaseObligations": "None",
          "longTermDebt": "6755563000",
          "currentLongTermDebt": "9557406000",
          "longTermDebtNoncurrent": "None",
          "shortLongTermDebtTotal": "6755563000",
          "otherCurrentLiabilities": "1859762000",
          "otherNonCurrentLiabilities": "2259538000",
          "totalShareholderEquity": "5105752000",
          "treasuryStock": "None",
          "retainedEarnings": "-3679584000",
          "commonStock": "163000",
          "commonStockSharesOutstanding": "166863000"
      },
      {
          "fiscalDateEnding": "2017-03-31",
          "reportedCurrency": "USD",
          "totalAssets": "25053726000",
          "totalCurrentAssets": "7027889000",
          "cashAndCashEquivalentsAtCarryingValue": "4006593000",
          "cashAndShortTermInvestments": "4006593000",
          "inventory": "2220336000",
          "currentNetReceivables": "440349000",
          "totalNonCurrentAssets": "330223000",
          "propertyPlantEquipment": "7016551000",
          "accumulatedDepreciationAmortizationPPE": "1164943000",
          "intangibleAssets": "429592000",
          "intangibleAssetsExcludingGoodwill": "388608000",
          "goodwill": "40984000",
          "investments": "None",
          "longTermInvestments": "486350000",
          "shortTermInvestments": "88946000",
          "otherCurrentAssets": "271665000",
          "otherNonCurrrentAssets": "224536000",
          "totalLiabilities": "18885353000",
          "totalCurrentLiabilities": "6245439000",
          "currentAccountsPayable": "2075333000",
          "deferredRevenue": "None",
          "currentDebt": "963737000",
          "shortTermDebt": "1003311000",
          "totalNonCurrentLiabilities": "10219570000",
          "capitalLeaseObligations": "None",
          "longTermDebt": "6927937000",
          "currentLongTermDebt": "1003311000",
          "longTermDebtNoncurrent": "None",
          "shortLongTermDebtTotal": "6927937000",
          "otherCurrentLiabilities": "1706428000",
          "otherNonCurrentLiabilities": "2081822000",
          "totalShareholderEquity": "4987719000",
          "treasuryStock": "None",
          "retainedEarnings": "-3343187000",
          "commonStock": "161000",
          "commonStockSharesOutstanding": "164164000"
      },
      {
          "fiscalDateEnding": "2016-12-31",
          "reportedCurrency": "USD",
          "totalAssets": "22664076000",
          "totalCurrentAssets": "6259796000",
          "cashAndCashEquivalentsAtCarryingValue": "3393000000",
          "cashAndShortTermInvestments": "3393000000",
          "inventory": "2067454000",
          "currentNetReceivables": "499142000",
          "totalNonCurrentAssets": "268000000",
          "propertyPlantEquipment": "5982957000",
          "accumulatedDepreciationAmortizationPPE": "997485000",
          "intangibleAssets": "376145000",
          "intangibleAssetsExcludingGoodwill": "376145000",
          "goodwill": "None",
          "investments": "None",
          "longTermInvestments": "506302000",
          "shortTermInvestments": "105519000",
          "otherCurrentAssets": "194465000",
          "otherNonCurrrentAssets": "216751000",
          "totalLiabilities": "16750167000",
          "totalCurrentLiabilities": "5827005000",
          "currentAccountsPayable": "1860341000",
          "deferredRevenue": "None",
          "currentDebt": "1114652000",
          "shortTermDebt": "1150147000",
          "totalNonCurrentLiabilities": "8640254000",
          "capitalLeaseObligations": "None",
          "longTermDebt": "5892016000",
          "currentLongTermDebt": "1210962000",
          "longTermDebtNoncurrent": "None",
          "shortLongTermDebtTotal": "5892016000",
          "otherCurrentLiabilities": "1606489000",
          "otherNonCurrentLiabilities": "1891449000",
          "totalShareholderEquity": "4752911000",
          "treasuryStock": "None",
          "retainedEarnings": "-2997237000",
          "commonStock": "161000",
          "commonStockSharesOutstanding": "161561000"
      },
      {
          "fiscalDateEnding": "2016-09-30",
          "reportedCurrency": "USD",
          "totalAssets": "12592397000",
          "totalCurrentAssets": "5172412000",
          "cashAndCashEquivalentsAtCarryingValue": "3084257000",
          "cashAndShortTermInvestments": "3084257000",
          "inventory": "1604571000",
          "currentNetReceivables": "326895000",
          "totalNonCurrentAssets": "4470688000",
          "propertyPlantEquipment": "4309048000",
          "accumulatedDepreciationAmortizationPPE": "912106000",
          "intangibleAssets": "None",
          "intangibleAssetsExcludingGoodwill": "None",
          "goodwill": "None",
          "investments": "None",
          "longTermInvestments": "None",
          "shortTermInvestments": "23711000",
          "otherCurrentAssets": "132978000",
          "otherNonCurrrentAssets": "70646000",
          "totalLiabilities": "9900639000",
          "totalCurrentLiabilities": "4082390000",
          "currentAccountsPayable": "1606284000",
          "deferredRevenue": "None",
          "currentDebt": "260771000",
          "shortTermDebt": "260771000",
          "totalNonCurrentLiabilities": "3762181000",
          "capitalLeaseObligations": "None",
          "longTermDebt": "200000000",
          "currentLongTermDebt": "260771000",
          "longTermDebtNoncurrent": "None",
          "shortLongTermDebtTotal": "200000000",
          "otherCurrentLiabilities": "1520317000",
          "otherNonCurrentLiabilities": "737559000",
          "totalShareholderEquity": "2680488000",
          "treasuryStock": "None",
          "retainedEarnings": "-2875900000",
          "commonStock": "150000",
          "commonStockSharesOutstanding": "149825000"
      },
      {
          "fiscalDateEnding": "2016-06-30",
          "reportedCurrency": "USD",
          "totalAssets": "11868952000",
          "totalCurrentAssets": "5203705000",
          "cashAndCashEquivalentsAtCarryingValue": "3246301000",
          "cashAndShortTermInvestments": "3246301000",
          "inventory": "1609607000",
          "currentNetReceivables": "178594000",
          "totalNonCurrentAssets": "4145721000",
          "propertyPlantEquipment": "3993250000",
          "accumulatedDepreciationAmortizationPPE": "783986000",
          "intangibleAssets": "None",
          "intangibleAssetsExcludingGoodwill": "None",
          "goodwill": "None",
          "investments": "38300000",
          "longTermInvestments": "None",
          "shortTermInvestments": "24525000",
          "otherCurrentAssets": "144678000",
          "otherNonCurrrentAssets": "66650000",
          "totalLiabilities": "9311512000",
          "totalCurrentLiabilities": "3766404000",
          "currentAccountsPayable": "1114878000",
          "deferredRevenue": "None",
          "currentDebt": "626826000",
          "shortTermDebt": "626826000",
          "totalNonCurrentLiabilities": "3765599000",
          "capitalLeaseObligations": "None",
          "longTermDebt": "1858685000",
          "currentLongTermDebt": "608900000",
          "longTermDebtNoncurrent": "1130000000",
          "shortLongTermDebtTotal": "1858685000",
          "otherCurrentLiabilities": "1466488000",
          "otherNonCurrentLiabilities": "612344000",
          "totalShareholderEquity": "2520294000",
          "treasuryStock": "None",
          "retainedEarnings": "-2897778000",
          "commonStock": "148000",
          "commonStockSharesOutstanding": "148015000"
      },
      {
          "fiscalDateEnding": "2016-03-31",
          "reportedCurrency": "USD",
          "totalAssets": "9191702000",
          "totalCurrentAssets": "3239543000",
          "cashAndCashEquivalentsAtCarryingValue": "1441789000",
          "cashAndShortTermInvestments": "1441789000",
          "inventory": "1301961000",
          "currentNetReceivables": "318056000",
          "totalNonCurrentAssets": "1909310000",
          "propertyPlantEquipment": "3593014000",
          "accumulatedDepreciationAmortizationPPE": "673089000",
          "intangibleAssets": "None",
          "intangibleAssetsExcludingGoodwill": "None",
          "goodwill": "None",
          "investments": "26800000",
          "longTermInvestments": "None",
          "shortTermInvestments": "23980000",
          "otherCurrentAssets": "153757000",
          "otherNonCurrrentAssets": "67152000",
          "totalLiabilities": "8178711000",
          "totalCurrentLiabilities": "3187699000",
          "currentAccountsPayable": "1013486000",
          "deferredRevenue": "None",
          "currentDebt": "635285000",
          "shortTermDebt": "635285000",
          "totalNonCurrentLiabilities": "3407937000",
          "capitalLeaseObligations": "None",
          "longTermDebt": "1937150000",
          "currentLongTermDebt": "617100000",
          "longTermDebtNoncurrent": "1220000000",
          "shortLongTermDebtTotal": "1937150000",
          "otherCurrentLiabilities": "709043000",
          "otherNonCurrentLiabilities": "426611000",
          "totalShareholderEquity": "970365000",
          "treasuryStock": "None",
          "retainedEarnings": "-2604590000",
          "commonStock": "134000",
          "commonStockSharesOutstanding": "133858000"
      }
  ]
}